setup.cfg
setup.py
pyidf/__init__.py
pyidf/advanced_construction.py
pyidf/air_distribution.py
pyidf/coils.py
pyidf/compliance_objects.py
pyidf/condenser_equipment_and_heat_exchangers.py
pyidf/controllers.py
pyidf/daylighting.py
pyidf/demand_limiting_controls.py
pyidf/detailed_ground_heat_transfer.py
pyidf/economics.py
pyidf/electric_load_center.py
pyidf/energy_management_system.py
pyidf/energyplus.py
pyidf/evaporative_coolers.py
pyidf/exterior_equipment.py
pyidf/external_interface.py
pyidf/fans.py
pyidf/fluid_properties.py
pyidf/general_data_entry.py
pyidf/heat_recovery.py
pyidf/helper.py
pyidf/humidifiers_and_dehumidifiers.py
pyidf/hvac_design_objects.py
pyidf/hvac_templates.py
pyidf/idf.py
pyidf/internal_gains.py
pyidf/location_and_climate.py
pyidf/natural_ventilation_and_duct_leakage.py
pyidf/node.py
pyidf/non.py
pyidf/operational_faults.py
pyidf/output_reporting.py
pyidf/parametrics.py
pyidf/performance_curves.py
pyidf/performance_tables.py
pyidf/plant.py
pyidf/plant_heating_and_cooling_equipment.py
pyidf/pumps.py
pyidf/refrigeration.py
pyidf/room_air_models.py
pyidf/schedules.py
pyidf/setpoint_managers.py
pyidf/simulation_parameters.py
pyidf/solar_collectors.py
pyidf/surface_construction_elements.py
pyidf/system_availability_managers.py
pyidf/thermal_zones_and_surfaces.py
pyidf/unitary_equipment.py
pyidf/user_defined_hvac_and_plant_component_models.py
pyidf/variable_refrigerant_flow_equipment.py
pyidf/water_heaters_and_thermal_storage.py
pyidf/water_systems.py
pyidf/zone_airflow.py
pyidf/zone_hvac_air_loop_terminal_units.py
pyidf/zone_hvac_controls_and_thermostats.py
pyidf/zone_hvac_equipment_connections.py
pyidf/zone_hvac_forced_air_units.py
pyidf/zone_hvac_radiative.py
pyidf.egg-info/PKG-INFO
pyidf.egg-info/SOURCES.txt
pyidf.egg-info/dependency_links.txt
pyidf.egg-info/top_level.txt