Metadata-Version: 1.1
Name: pyidf
Version: 0.2.0
Summary: Python library to read, modify and create EnergyPlus idf files
Home-page: https://github.com/rbuffat/pyidf
Author: Rene Buffat
Author-email: buffat@gmail.com
License: Apache License 2.0
Download-URL: https://github.com/rbuffat/pyidf/tarball/0.2.0
Keywords: EnergyPlus,IDF
Platform: UNKNOWN
Classifier: Development Status :: 3 - Alpha
